aiosteady/__init__.py
aiosteady/leakybucket.py
aiosteady/leakybucket_consume.lua
aiosteady/leakybucket_peek.lua
aiosteady/py.typed
aiosteady-22.1.0.dist-info/LICENSE
aiosteady-22.1.0.dist-info/WHEEL
aiosteady-22.1.0.dist-info/METADATA
aiosteady-22.1.0.dist-info/RECORD
