Metadata-Version: 2.1
Name: aiosteady
Version: 22.1.0
Summary: Rate limiting for asyncio
License: MIT
Author: Tin Tvrtkovic
Author-email: tinchester@gmail.com
Requires-Python: >=3.8,<4.0
Classifier: License :: OSI Approved :: MIT License
Classifier: Programming Language :: Python :: 3
Classifier: Programming Language :: Python :: 3.8
Classifier: Programming Language :: Python :: 3.9
Classifier: Programming Language :: Python :: 3.10
Requires-Dist: aioredis (>=1.3.1,<2.0.0)
Requires-Dist: attrs (>=20.3.0)
